AUTHORS
CHANGELOG.txt
DESCRIPTION
LICENSE
MANIFEST.in
README.rst
setup.py
inb_django_influxdb_metrics.egg-info/PKG-INFO
inb_django_influxdb_metrics.egg-info/SOURCES.txt
inb_django_influxdb_metrics.egg-info/dependency_links.txt
inb_django_influxdb_metrics.egg-info/requires.txt
inb_django_influxdb_metrics.egg-info/top_level.txt
influxdb_metrics/__init__.py
influxdb_metrics/email.py
influxdb_metrics/loader.py
influxdb_metrics/middleware.py
influxdb_metrics/models.py
influxdb_metrics/pool.py
influxdb_metrics/tasks.py
influxdb_metrics/utils.py
influxdb_metrics/management/__init__.py
influxdb_metrics/management/commands/__init__.py
influxdb_metrics/management/commands/influxdb_get_postgresql_size.py
influxdb_metrics/tests/__init__.py
influxdb_metrics/tests/email_tests.py
influxdb_metrics/tests/influxdb_get_postgresql_size_tests.py
influxdb_metrics/tests/middleware_tests.py
influxdb_metrics/tests/models_tests.py
influxdb_metrics/tests/real_connection_tests.py
influxdb_metrics/tests/settings.py
influxdb_metrics/tests/test_settings.py
influxdb_metrics/tests/urls.py
influxdb_metrics/tests/utils_tests.py