Metadata-Version: 1.0
Name: inb-django-influxdb-metrics
Version: 1.3.3
Summary: A reusable Django app that sends metrics about your project to InfluxDB
